README.rst
setup.py
score/__init__.py
score.php.egg-info/PKG-INFO
score.php.egg-info/SOURCES.txt
score.php.egg-info/dependency_links.txt
score.php.egg-info/namespace_packages.txt
score.php.egg-info/not-zip-safe
score.php.egg-info/requires.txt
score.php.egg-info/top_level.txt
score/php/__init__.py
score/php/_init.py
score/php/engine.py
score/php/worker.py