Metadata-Version: 1.0
Name: score.php
Version: 0.0.1
Summary: UNKNOWN
Home-page: http://score-framework.org
Author: strg.at
Author-email: score@strg.at
License: LGPL
Keywords: score framework php templating
Platform: UNKNOWN
